gptool/__init__.py
gptool/config.py
gptool/gptool.py
gptool/services/defaultvectordb_service.py
gptool/services/openai_service.py
gptool/types/abstract_vectordb.py
gptool/types/function.py
gptool/types/log_level.py
gptool/utils/file_utilities.py
gptool/utils/format_config_args.py
gptool/utils/inspection_utilities.py
gptool/utils/logger.py
gptool/utils/model_utilities.py
gptool/utils/openai_utilities.py
gptool-0.1.4.dist-info/LICENSE
gptool-0.1.4.dist-info/METADATA
gptool-0.1.4.dist-info/WHEEL
gptool-0.1.4.dist-info/RECORD
